{
  "$schema": "https://developer.microsoft.com/json-schemas/spfx-build/package-solution.schema.json",
  "solution": {
    "name": "xenwp-uco-bank-client-side-solution",
    "id": "64c83995-d513-45bc-834c-775c6b3e09ee",
    "version": "1.0.0.2",
    "includeClientSideAssets": true,
    "skipFeatureDeployment": true,
    "isDomainIsolated": false,
 
    "developer": {
      "name": "",
      "websiteUrl": "",
      "privacyUrl": "",
      "termsOfUseUrl": "",
      "mpnId": "Undefined-1.19.0"
    },
    "metadata": {
      "shortDescription": {
        "default": "xenwpUcoBank description"
      },
      "longDescription": {
        "default": "xenwpUcoBank description"
      },
      "screenshotPaths": [],
      "videoUrl": "",
      "categories": []
    },
    "features": [
      {
        "title": "xenwp-uco-bank Feature",
        "description": "The feature that activates elements of the xenwp-uco-bank solution.",
        "id": "71a6c1b3-edce-4903-91c8-80c5943ec1d6",
        "version": "1.0.0.2"
      }
    ]
  },
  "paths": {
    "zippedPackage": "solution/xenwp-uco-bank.sppkg"
  }
}
